pcdebuginformation/__init__.py
pcdebuginformation/information.py
pcdebuginformation-0.0.4.dist-info/LICENSE
pcdebuginformation-0.0.4.dist-info/METADATA
pcdebuginformation-0.0.4.dist-info/WHEEL
pcdebuginformation-0.0.4.dist-info/top_level.txt
pcdebuginformation-0.0.4.dist-info/RECORD
