Metadata-Version: 2.1
Name: pcdebuginformation
Version: 0.0.4
Summary: This package will extract all the important details from linux system and create a report.
Author-email: Ravi Nain <ravinain100@gmail.com>
Project-URL: Homepage, https://github.com/qaravinain/hybridtoolkit
Project-URL: Bug Tracker, https://github.com/qaravinain/hybridtoolkit/issues
Project-URL: Linked In, https://www.linkedin.com/in/ravi-nain-2029691a0/
Classifier: Programming Language :: Python :: 3
Classifier: License :: OSI Approved :: MIT License
Classifier: Operating System :: OS Independent
Requires-Python: >=3.6
License-File: LICENSE
